swane_supplement/__init__.py
swane_supplement/icons/error.svg
swane_supplement/icons/load.svg
swane_supplement/icons/ok.svg
swane_supplement/icons/swane.icns
swane_supplement/icons/swane.png
swane_supplement/icons/swane_logo.png
swane_supplement/icons/void.svg
swane_supplement/icons/warn.svg
swane_supplement/resources/mni_icbm152_t1_tal_nlin_sym_09c_brain.nii.gz
swane_supplement/resources/doMAP_template/binary_cerebellum.nii.gz
swane_supplement/resources/doMAP_template/brain_cortex_mas_OK.nii.gz
swane_supplement/resources/doMAP_template/brain_cortex_mas_OK.nii_2.gz
swane_supplement/resources/doMAP_template/mean_extension.nii.gz
swane_supplement/resources/doMAP_template/mean_flair.nii.gz
swane_supplement/resources/doMAP_template/std_final_extension.nii.gz
swane_supplement/resources/doMAP_template/std_final_flair.nii.gz
swane_supplement-0.1.2.dist-info/LICENSE
swane_supplement-0.1.2.dist-info/METADATA
swane_supplement-0.1.2.dist-info/WHEEL
swane_supplement-0.1.2.dist-info/top_level.txt
swane_supplement-0.1.2.dist-info/RECORD
