Metadata-Version: 2.1
Name: swane-supplement
Version: 0.1.2
Summary: Standardized Workflow for Advanced Neuroimaging in Epilepsy - supplementary files
Author-email: LICE - Commissione Neuroimmagini <dev@lice.it>
Classifier: Programming Language :: Python :: 3
Classifier: License :: OSI Approved :: MIT License
Classifier: Operating System :: MacOS
Classifier: Operating System :: POSIX :: Linux
Requires-Python: >=3.7
License-File: LICENSE
